[{"createAt":1510912704000,"id":1,"k":"0","type":"sex","updateAt":1511014865000,"val":"女"},{"createAt":1510913026000,"id":2,"k":"1","type":"sex","updateAt":1600116075000,"val":"男"},{"createAt":1510935966000,"id":3,"k":"0","type":"userStatus","updateAt":1510935969000,"val":"无效"},{"createAt":1510935966000,"id":4,"k":"1","type":"userStatus","updateAt":1510935969000,"val":"正常"},{"createAt":1510935966000,"id":5,"k":"2","type":"userStatus","updateAt":1510935969000,"val":"锁定"},{"createAt":1510935966000,"id":6,"k":"0","type":"noticeStatus","updateAt":1510935969000,"val":"草稿"},{"createAt":1510935966000,"id":7,"k":"1","type":"noticeStatus","updateAt":1510935969000,"val":"发布"},{"createAt":1510935966000,"id":8,"k":"0","type":"isRead","updateAt":1510935969000,"val":"未读"},{"createAt":1510935966000,"id":9,"k":"1","type":"isRead","updateAt":1510935969000,"val":"已读"}]